whatsbot/__init__.py
whatsapp_python_client-0.0.1.dist-info/METADATA
whatsapp_python_client-0.0.1.dist-info/WHEEL
whatsapp_python_client-0.0.1.dist-info/top_level.txt
whatsapp_python_client-0.0.1.dist-info/RECORD
